libcove/__init__.py
libcove/config.py
libcove/lib/__init__.py
libcove/lib/common.py
libcove/lib/converters.py
libcove/lib/exceptions.py
libcove/lib/tools.py
libcove-0.32.1.dist-info/LICENSE
libcove-0.32.1.dist-info/METADATA
libcove-0.32.1.dist-info/WHEEL
libcove-0.32.1.dist-info/top_level.txt
libcove-0.32.1.dist-info/RECORD
