Metadata-Version: 2.1
Name: libcove
Version: 0.32.1
Summary: A data review library
Home-page: https://github.com/OpenDataServices/lib-cove
Author: Open Data Services
Author-email: code@opendataservices.coop
License: UNKNOWN
Platform: UNKNOWN
Classifier: License :: OSI Approved :: GNU Affero General Public License v3 or later (AGPLv3+)
License-File: LICENSE
